fistnd/FIST.py
fistnd/__init__.py
fistnd/__main__.py
fistnd/algorithm.py
fistnd/error.py
fistnd/postprocessing.py
fistnd/preprocessing.py
fistnd/report.py
fistnd/visualize_before_after.py
fistnd-0.1.0.dist-info/LICENSE
fistnd-0.1.0.dist-info/METADATA
fistnd-0.1.0.dist-info/WHEEL
fistnd-0.1.0.dist-info/top_level.txt
fistnd-0.1.0.dist-info/RECORD
