Metadata-Version: 2.1
Name: fistnd
Version: 0.1.0
Summary: FIST-nD, Fast Imputation of Spatially-resolved transcriptomes by graph-regularized Tensor completion in n-Dimensions imputes 3D as well as 2D spatial transcriptomics data.
Home-page: https://github.com/kuanglab/FIST-nD
Author: Rui Kuang
Author-email: Rui Kuang <kuang@umn.edu>
Project-URL: Homepage, https://github.com/kuanglab/FIST-nD
Project-URL: Bug Tracker, https://github.com/kuanglab/FIST-nD/issues
Classifier: Programming Language :: Python :: 3
Classifier: License :: OSI Approved :: MIT License
Classifier: Operating System :: OS Independent
Requires-Python: >=3.7
License-File: LICENSE
Requires-Dist: matplotlib (>=3.4.3)
Requires-Dist: numpy (>=1.21.2)
Requires-Dist: pandas (>=1.3.3)
Requires-Dist: pillow (>=8.4.0)
Requires-Dist: scipy (>=1.7.1)
Requires-Dist: mygene (>=3.2.2)
Requires-Dist: scikit-learn (>=1.0.1)
Requires-Dist: tensorly (>=0.6.0)
Requires-Dist: python-dateutil (>=2.8.1)
Requires-Dist: pyarrow (>=9.0.0)
Requires-Dist: torch
